drakrun/__init__.py
drakrun/version.py
drakrun/analyzer/__init__.py
drakrun/analyzer/analysis_options.py
drakrun/analyzer/analyzer.py
drakrun/analyzer/file_metadata.py
drakrun/analyzer/post_restore.py
drakrun/analyzer/run_tools.py
drakrun/analyzer/screenshotter.py
drakrun/analyzer/startup_command.py
drakrun/analyzer/worker.py
drakrun/analyzer/postprocessing/__init__.py
drakrun/analyzer/postprocessing/indexer.py
drakrun/analyzer/postprocessing/postprocess.py
drakrun/analyzer/postprocessing/process_tree.py
drakrun/analyzer/postprocessing/plugins/__init__.py
drakrun/analyzer/postprocessing/plugins/build_process_tree.py
drakrun/analyzer/postprocessing/plugins/compress_ipt.py
drakrun/analyzer/postprocessing/plugins/generate_report.py
drakrun/analyzer/postprocessing/plugins/generate_wireshark_key_file.py
drakrun/analyzer/postprocessing/plugins/get_http_info.py
drakrun/analyzer/postprocessing/plugins/get_modified_files_info.py
drakrun/analyzer/postprocessing/plugins/get_socket_info.py
drakrun/analyzer/postprocessing/plugins/get_ttps_info.py
drakrun/analyzer/postprocessing/plugins/gzip_syscalls.py
drakrun/analyzer/postprocessing/plugins/index_logs.py
drakrun/analyzer/postprocessing/plugins/parse_utils.py
drakrun/analyzer/postprocessing/plugins/plugin_base.py
drakrun/analyzer/postprocessing/plugins/process_dumps.py
drakrun/analyzer/postprocessing/plugins/screenshot_metadata.py
drakrun/analyzer/postprocessing/plugins/split_drakmon_log.py
drakrun/analyzer/postprocessing/plugins/capa_plugin/__init__.py
drakrun/analyzer/postprocessing/plugins/capa_plugin/capa_processor.py
drakrun/cli/__init__.py
drakrun/cli/__main__.py
drakrun/cli/analyze.py
drakrun/cli/banner.py
drakrun/cli/check_root.py
drakrun/cli/drakshell.py
drakrun/cli/drakvuf_cmdline.py
drakrun/cli/injector.py
drakrun/cli/install.py
drakrun/cli/main.py
drakrun/cli/make_profile.py
drakrun/cli/modify_vm0.py
drakrun/cli/mount.py
drakrun/cli/postinstall.py
drakrun/cli/postprocess.py
drakrun/cli/s3_storage.py
drakvuf_sandbox-0.20.0.dist-info/licenses/COPYING
drakvuf_sandbox-0.20.0.dist-info/licenses/LICENSE
drakvuf_sandbox-0.20.0.dist-info/METADATA
drakvuf_sandbox-0.20.0.dist-info/WHEEL
drakvuf_sandbox-0.20.0.dist-info/entry_points.txt
drakvuf_sandbox-0.20.0.dist-info/top_level.txt
drakvuf_sandbox-0.20.0.dist-info/RECORD
